<Properties StartupConfiguration="{3184575F-EE13-4A6E-9586-E1815E0B6FB4}|Default">
  <MonoDevelop.Ide.ItemProperties.0__3LongerLine PreferredExecutionTarget="MonoDevelop.Default" />
  <MonoDevelop.Ide.Workbench ActiveDocument="0_3LongerLine/Program.cs">
    <Files>
      <File FileName="0_3LongerLine/Program.cs" Line="62" Column="18" />
    </Files>
  </MonoDevelop.Ide.Workbench>
  <MonoDevelop.Ide.DebuggingService.PinnedWatches />
  <MonoDevelop.Ide.Workspace ActiveConfiguration="Debug" />
  <MonoDevelop.Ide.DebuggingService.Breakpoints>
    <BreakpointStore />
  </MonoDevelop.Ide.DebuggingService.Breakpoints>
  <MultiItemStartupConfigurations />
</Properties>