<Properties StartupConfiguration="{E8C0F163-7E2B-4E7B-B8AE-CEA38294AEDD}|Default">
  <MonoDevelop.Ide.Workbench ActiveDocument="1_6StrongNumber/Program.cs">
    <Files>
      <File FileName="1_6StrongNumber/Program.cs" Line="13" Column="14" />
    </Files>
  </MonoDevelop.Ide.Workbench>
  <MonoDevelop.Ide.DebuggingService.PinnedWatches />
  <MonoDevelop.Ide.Workspace ActiveConfiguration="Debug" />
  <MonoDevelop.Ide.DebuggingService.Breakpoints>
    <BreakpointStore />
  </MonoDevelop.Ide.DebuggingService.Breakpoints>
  <MultiItemStartupConfigurations />
  <MonoDevelop.Ide.ItemProperties.1__6StrongNumber PreferredExecutionTarget="MonoDevelop.Default" />
</Properties>